pymuster/__init__.py
pymuster/cli/__init__.py
pymuster/cli/cli.py
pymuster/core/__init__.py
pymuster/core/field_calculus.py
pymuster/core/losses.py
pymuster/core/utils.py
pymuster/muster.py
pymuster/muster_lin.npy
pymuster-0.1.10.dist-info/LICENSE
pymuster-0.1.10.dist-info/METADATA
pymuster-0.1.10.dist-info/WHEEL
pymuster-0.1.10.dist-info/entry_points.txt
pymuster-0.1.10.dist-info/RECORD
